krikzz_pub_archive_tool/__init__.py
krikzz_pub_archive_tool-0.0.2.dist-info/LICENSE
krikzz_pub_archive_tool-0.0.2.dist-info/METADATA
krikzz_pub_archive_tool-0.0.2.dist-info/WHEEL
krikzz_pub_archive_tool-0.0.2.dist-info/entry_points.txt
krikzz_pub_archive_tool-0.0.2.dist-info/top_level.txt
krikzz_pub_archive_tool-0.0.2.dist-info/RECORD
